vercel_ai/__init__.py
vercel_ai/py.typed
vercel_ai/adapter/__init__.py
vercel_ai/adapter/manager.py
vercel_ai/adapter/messages.py
vercel_ai/adapter/parts.py
vercel_ai/fastapi/__init__.py
vercel_ai/providers/__init__.py
vercel_ai/providers/openai.py
vercel_ai-0.1.0.dist-info/METADATA
vercel_ai-0.1.0.dist-info/WHEEL
vercel_ai-0.1.0.dist-info/RECORD
